pyreinfolib/__init__.py
pyreinfolib/client.py
pyreinfolib/enums.py
pyreinfolib/test.py
pyreinfolib-0.1.0.dist-info/METADATA
pyreinfolib-0.1.0.dist-info/WHEEL
pyreinfolib-0.1.0.dist-info/licenses/LICENSE
pyreinfolib-0.1.0.dist-info/RECORD
