Metadata-Version: 2.3
Name: pyreinfolib
Version: 0.1.0
Summary: Python client for Real Estate Information Library APIs
Project-URL: Homepage, https://github.com/matsudan/pyreinfolib
Author-email: matsudan <daaamatsun@gmail.com>
Keywords: api,client,real-estate
Classifier: License :: OSI Approved :: MIT License
Classifier: Operating System :: OS Independent
Classifier: Programming Language :: Python :: 3
Classifier: Programming Language :: Python :: 3.11
Classifier: Programming Language :: Python :: 3.12
Requires-Python: >=3.11
Requires-Dist: requests
